h3converter/__init__.py
h3converter/h3converter.py
h3converter/libh3.1.dylib
h3converter/libh3.dylib
h3converter/libh3.so
h3converter/libh3.so.1
tests/__init__.py
tests/testh3converter.py
h3converter-0.1.0.dist-info/LICENSE.txt
h3converter-0.1.0.dist-info/METADATA
h3converter-0.1.0.dist-info/WHEEL
h3converter-0.1.0.dist-info/top_level.txt
h3converter-0.1.0.dist-info/RECORD
