Metadata-Version: 2.1
Name: h3converter
Version: 0.1.0
Summary: This package helps you convert h3 hec code directly to geojson and a GeoJSON entity to h3 hex code
Home-page: https://github.com/kapil-grv/h3converter
Author: Kapil Gauravan V
Author-email: kapilgrv@gmail.com
License: UNKNOWN
Project-URL: Bug Tracker, https://github.com/kapil-grv/h3converter/issues
Platform: UNKNOWN
Classifier: Programming Language :: Python :: 3
Classifier: License :: OSI Approved :: MIT License
Classifier: Operating System :: OS Independent
Requires-Python: >=3.6
Requires-Dist: geojson
